ssg_sea/VERSION
ssg_sea/__init__.py
ssg_sea/extract_skills.py
ssg_sea/params.yaml
ssg_sea/utils.py
ssg_sea/config/__init__.py
ssg_sea/config/core.py
ssg_sea/data/pickle.pkl
ssg_sea-1.6.0.dist-info/METADATA
ssg_sea-1.6.0.dist-info/WHEEL
ssg_sea-1.6.0.dist-info/top_level.txt
ssg_sea-1.6.0.dist-info/RECORD
