Metadata-Version: 2.1
Name: ssg-sea
Version: 1.6.0
Summary: Skills Extraction Algorithm to extract skills from free text based on Singapore Skills Taxonomy (SST)
Home-page: https://github.com/ssg-leo/SSG-SEA/
Author: LeoLi
Author-email: leo_li@ssg.gov.sg
License: BSD-3
Classifier: License :: OSI Approved :: MIT License
Classifier: Programming Language :: Python
Classifier: Programming Language :: Python :: 3
Classifier: Programming Language :: Python :: 3.6
Classifier: Programming Language :: Python :: 3.7
Classifier: Programming Language :: Python :: 3.8
Classifier: Programming Language :: Python :: 3.9
Classifier: Programming Language :: Python :: Implementation :: CPython
Classifier: Programming Language :: Python :: Implementation :: PyPy
Requires-Python: >=3.6.0
Requires-Dist: pandas (<1.4.3,>=1.4.1)
Requires-Dist: pyyaml (<6.2,>=5.0)
Requires-Dist: flashtext (~=2.7)
Requires-Dist: tqdm (>=4.64.0)
